valuecounts/__init__.py
valuecounts-0.1.dist-info/LICENSE.txt
valuecounts-0.1.dist-info/METADATA
valuecounts-0.1.dist-info/WHEEL
valuecounts-0.1.dist-info/top_level.txt
valuecounts-0.1.dist-info/RECORD
