Metadata-Version: 2.1
Name: valuecounts
Version: 0.1
Summary: I will greet you
Home-page: https://github.com/klmsathish/greeter
Author: klmsathish
Author-email: klmsathish@gmail.com
License: MIT
Keywords: value_counts
Platform: UNKNOWN
